pyafc/__init__.py
pyafc/afc/__init__.py
pyafc/afc/afc.py
pyafc/afc/backups.py
pyafc/afc/licenses.py
pyafc/afc/models.py
pyafc/common/__init__.py
pyafc/common/exceptions.py
pyafc/common/internal.py
pyafc/common/utils.py
pyafc/dss/__init__.py
pyafc/dss/dss.py
pyafc/dss/endpoint_groups.py
pyafc/dss/models.py
pyafc/dss/policies.py
pyafc/dss/qualifiers.py
pyafc/dss/rules.py
pyafc/dss/vnic_moves.py
pyafc/fabric/__init__.py
pyafc/fabric/evpn.py
pyafc/fabric/fabric.py
pyafc/fabric/leaf_spine.py
pyafc/fabric/models.py
pyafc/fabric/multi_fabrics.py
pyafc/fabric/pvlan.py
pyafc/fabric/vsx.py
pyafc/fabric/vxlan.py
pyafc/integrations/__init__.py
pyafc/integrations/integrations.py
pyafc/integrations/models.py
pyafc/integrations/psm.py
pyafc/integrations/vmware.py
pyafc/integrations/vswitches.py
pyafc/models/__init__.py
pyafc/models/afc.py
pyafc/ports/__init__.py
pyafc/ports/lag.py
pyafc/ports/models.py
pyafc/ports/physical.py
pyafc/ports/ports.py
pyafc/ports/vlan_group.py
pyafc/route_policies/__init__.py
pyafc/route_policies/as_path_lists.py
pyafc/route_policies/community_lists.py
pyafc/route_policies/models.py
pyafc/route_policies/prefix_lists.py
pyafc/route_policies/route_maps.py
pyafc/route_policies/route_policy.py
pyafc/services/__init__.py
pyafc/services/checkpoints.py
pyafc/services/dhcp_relay.py
pyafc/services/dns.py
pyafc/services/models.py
pyafc/services/ntp.py
pyafc/services/radius.py
pyafc/services/resource_pools.py
pyafc/services/services.py
pyafc/services/sflow.py
pyafc/services/snmp.py
pyafc/services/stp.py
pyafc/services/syslog.py
pyafc/switches/__init__.py
pyafc/switches/cli.py
pyafc/switches/models.py
pyafc/switches/switches.py
pyafc/vrf/__init__.py
pyafc/vrf/bgp.py
pyafc/vrf/ip_interfaces.py
pyafc/vrf/models.py
pyafc/vrf/networks.py
pyafc/vrf/ospf.py
pyafc/vrf/overlay.py
pyafc/vrf/static_routes.py
pyafc/vrf/underlay.py
pyafc/vrf/vrf.py
workflows/__init__.py
workflows/assign_fabric.py
workflows/configure_overlay.py
workflows/configure_ports.py
pyafc-1.0.1.dist-info/METADATA
pyafc-1.0.1.dist-info/WHEEL
pyafc-1.0.1.dist-info/top_level.txt
pyafc-1.0.1.dist-info/RECORD
