Metadata-Version: 2.4
Name: pyafc
Version: 1.0.1
Summary: AFC Python Modules
Home-page: https://github.com/aruba/pyafc
Author: Aruba Automation
Author-email: aruba-automation@hpe.com
License: Apache 2.0
Keywords: networking aruba fabric composer rest api python
Classifier: Development Status :: 5 - Production/Stable
Classifier: Intended Audience :: System Administrators
Classifier: Topic :: System :: Networking
Classifier: License :: OSI Approved :: Apache Software License
Classifier: Programming Language :: Python :: 3 :: Only
Requires-Python: >=3.6
Requires-Dist: requests
Requires-Dist: PyYAML
Requires-Dist: netaddr
Requires-Dist: requests_toolbelt
Requires-Dist: wheel
Requires-Dist: pydantic==1.10.12
Requires-Dist: httpx
Dynamic: author
Dynamic: author-email
Dynamic: classifier
Dynamic: description
Dynamic: description-content-type
Dynamic: home-page
Dynamic: keywords
Dynamic: license
Dynamic: requires-dist
Dynamic: requires-python
Dynamic: summary
